<monster>
	<name></name>
	<size></size>
	<type></type>
	<alignment></alignment>
	<ac></ac>
	<hp></hp>
	<speed></speed>
	<str></str><dex></dex><con></con><int></int><wis></wis><cha></cha>
	<save></save>
	<skill></skill>
	<resist></resist>
	<vulnerable></vulnerable>
	<immune></immune>
	<conditionImmune></conditionImmune>
	<senses></senses>
	<passive></passive>
	<languages></languages>
	<cr></cr>
	<trait>
		<name></name>
		<text></text>
	</trait>
	<action>
		<name></name>
		<text></text>
		<attack>||</attack>
	</action>
	<reaction>
		<name></name>
		<text></text>
		<attack>||</attack>
	</reaction>
	<legendary>
		<name></name>
		<text></text>
		<attack>||</attack>
	</legendary>
	<spells></spells>
</monster>